oculoenv/__init__.py
oculoenv/__version__.py
oculoenv/environment.py
oculoenv/geom.py
oculoenv/graphics.py
oculoenv/objmesh.py
oculoenv/utils.py
oculoenv/contents/__init__.py
oculoenv/contents/base_content.py
oculoenv/contents/change_detection_content.py
oculoenv/contents/multiple_object_tracking_content.py
oculoenv/contents/odd_one_out_content.py
oculoenv/contents/point_to_target_content.py
oculoenv/contents/random_dot_content.py
oculoenv/contents/visual_search_content.py
oculoenv/data/meshes/frame0.mtl
oculoenv/data/meshes/frame0.obj
oculoenv/data/textures/arrow0.png
oculoenv/data/textures/arrow1.png
oculoenv/data/textures/dot0.png
oculoenv/data/textures/frame0.png
oculoenv/data/textures/general_e0.png
oculoenv/data/textures/general_h_bar0.png
oculoenv/data/textures/general_l0.png
oculoenv/data/textures/general_l1.png
oculoenv/data/textures/general_plus0.png
oculoenv/data/textures/general_r0.png
oculoenv/data/textures/general_r1.png
oculoenv/data/textures/general_rect0.png
oculoenv/data/textures/general_round0.png
oculoenv/data/textures/general_s0.png
oculoenv/data/textures/general_t0.png
oculoenv/data/textures/general_t1.png
oculoenv/data/textures/general_v_bar0.png
oculoenv/data/textures/general_z0.png
oculoenv/data/textures/start_marker0.png
oculoenv/data/textures/white0.png
oculoenv-0.1.3.dist-info/METADATA
oculoenv-0.1.3.dist-info/RECORD
oculoenv-0.1.3.dist-info/WHEEL
oculoenv-0.1.3.dist-info/top_level.txt
tests/contents/__init__.py
tests/contents/change_detection_content_test.py
tests/contents/multiple_object_tracking_content_test.py
tests/contents/odd_one_out_content_test.py
tests/contents/point_to_target_content_test.py
tests/contents/random_dot_content_test.py
tests/contents/visual_search_content_test.py
